QB_solver-0.1.9.data/scripts/run_simulation
qb_solver/__init__.py
qb_solver/__main__.py
qb_solver/cubebasics.py
qb_solver/cubesolver.py
qb_solver/virtualcube.py
qb_solver/visCube.py
qb_solver/visHints.py
qb_solver/Models/Arrow.obj
qb_solver/Models/B.obj
qb_solver/Models/BO.obj
qb_solver/Models/BR.obj
qb_solver/Models/G.obj
qb_solver/Models/GO.obj
qb_solver/Models/GR.obj
qb_solver/Models/HintDetail1.png
qb_solver/Models/HintDetail2.png
qb_solver/Models/HintDetail3.png
qb_solver/Models/HintDetail4.png
qb_solver/Models/HintDetail5.png
qb_solver/Models/HintDetail6.png
qb_solver/Models/HintDetail7.png
qb_solver/Models/O.obj
qb_solver/Models/Picture1.png
qb_solver/Models/Picture2.png
qb_solver/Models/R.obj
qb_solver/Models/RubiksTex.png
qb_solver/Models/ShowNotation.png
qb_solver/Models/W.obj
qb_solver/Models/WB.obj
qb_solver/Models/WBR.obj
qb_solver/Models/WG.obj
qb_solver/Models/WGO.obj
qb_solver/Models/WO.obj
qb_solver/Models/WOB.obj
qb_solver/Models/WR.obj
qb_solver/Models/WRG.obj
qb_solver/Models/Y.obj
qb_solver/Models/YB.obj
qb_solver/Models/YBO.obj
qb_solver/Models/YG.obj
qb_solver/Models/YGR.obj
qb_solver/Models/YO.obj
qb_solver/Models/YOG.obj
qb_solver/Models/YR.obj
qb_solver/Models/YRB.obj
qb_solver/Models/aboutus_button.png
qb_solver/Models/aboutus_text.png
qb_solver/Models/circle.png
qb_solver/Models/colorblind.png
qb_solver/Models/colorblind2.png
qb_solver/Models/colorscheme2.png
qb_solver/Models/cubetest.obj
qb_solver/Models/gear.png
qb_solver/Models/gear_light.png
qb_solver/Models/hint1.png
qb_solver/Models/hint2.png
qb_solver/Models/hint3.png
qb_solver/Models/hint4.png
qb_solver/Models/hint5.png
qb_solver/Models/hint6.png
qb_solver/Models/hint7.png
qb_solver/Models/hint8.png
qb_solver/Models/hintButton.png
qb_solver/Models/hints_button.png
qb_solver/Models/impossiblegame.wav
qb_solver/Models/input_button.png
qb_solver/Models/key1.png
qb_solver/Models/key2.png
qb_solver/Models/menu_button.png
qb_solver/Models/next.png
qb_solver/Models/next2.png
QB_solver-0.1.9.dist-info/METADATA
QB_solver-0.1.9.dist-info/WHEEL
QB_solver-0.1.9.dist-info/top_level.txt
QB_solver-0.1.9.dist-info/RECORD
