Metadata-Version: 2.1
Name: QB-solver
Version: 0.1.9
Summary: Rubik's cube simulation and tutorial
Home-page: https://github.com/a-penton/QB
Author: Andrew Penton, Heinrich Perez, Steven Perez, Noah Sharpe, Daniel Shinkarow
Author-email: andrew.penton@gmail.com
License: GPL3
Platform: UNKNOWN
Requires-Dist: ursina (==3.5.0)
Requires-Dist: rubik-cube (==0.0.1)
Requires-Dist: psd-tools3 (==1.8.2)
